similarix/__init__.py
similarix/client.py
similarix-0.1.0.dist-info/LICENSE
similarix-0.1.0.dist-info/METADATA
similarix-0.1.0.dist-info/WHEEL
similarix-0.1.0.dist-info/top_level.txt
similarix-0.1.0.dist-info/RECORD
