Metadata-Version: 2.1
Name: similarix
Version: 0.1.0
Summary: Python client for Similarix API: Semantic and multimodal search engine for images and text
Author-email: Simeon Emanuilov <simeon.emanuilov@gmail.com>
License: Apache License
Project-URL: Homepage, https://github.com/s-emanuilov/similarix-client
Project-URL: Bug Tracker, https://github.com/s-emanuilov/similarix-client/issues
Project-URL: Documentation, https://github.com/s-emanuilov/similarix-client#readme
Project-URL: Source Code, https://github.com/s-emanuilov/similarix-client
Keywords: semantic search,multimodal search,image search,text search,ai search,similarity search,search engine,semantic search api,content-based search,visual search
Classifier: Development Status :: 4 - Beta
Classifier: Intended Audience :: Developers
Classifier: Topic :: Software Development :: Libraries :: Python Modules
Classifier: Topic :: Internet :: WWW/HTTP
Classifier: Topic :: Scientific/Engineering :: Artificial Intelligence
Classifier: Topic :: Multimedia :: Graphics
Classifier: Topic :: Text Processing :: Indexing
Classifier: Programming Language :: Python :: 3
Classifier: Programming Language :: Python :: 3.6
Classifier: Programming Language :: Python :: 3.7
Classifier: Programming Language :: Python :: 3.8
Classifier: Programming Language :: Python :: 3.9
Classifier: Programming Language :: Python :: 3.10
Classifier: License :: OSI Approved :: MIT License
Classifier: Operating System :: OS Independent
Requires-Python: >=3.6
License-File: LICENSE
